odoo/addons/stock_picking_return_restricted_qty/README.rst
odoo/addons/stock_picking_return_restricted_qty/__init__.py
odoo/addons/stock_picking_return_restricted_qty/__manifest__.py
odoo/addons/stock_picking_return_restricted_qty/i18n/es.po
odoo/addons/stock_picking_return_restricted_qty/i18n/it.po
odoo/addons/stock_picking_return_restricted_qty/i18n/pt_BR.po
odoo/addons/stock_picking_return_restricted_qty/i18n/stock_picking_return_restricted_qty.pot
odoo/addons/stock_picking_return_restricted_qty/i18n/zh_CN.po
odoo/addons/stock_picking_return_restricted_qty/models/__init__.py
odoo/addons/stock_picking_return_restricted_qty/models/stock_picking_type.py
odoo/addons/stock_picking_return_restricted_qty/readme/CONFIGURE.md
odoo/addons/stock_picking_return_restricted_qty/readme/CONTRIBUTORS.md
odoo/addons/stock_picking_return_restricted_qty/readme/DESCRIPTION.md
odoo/addons/stock_picking_return_restricted_qty/readme/USAGE.md
odoo/addons/stock_picking_return_restricted_qty/static/description/icon.png
odoo/addons/stock_picking_return_restricted_qty/static/description/index.html
odoo/addons/stock_picking_return_restricted_qty/tests/__init__.py
odoo/addons/stock_picking_return_restricted_qty/tests/test_stock_picking_return_restricted_qty.py
odoo/addons/stock_picking_return_restricted_qty/views/stock_picking_type_views.xml
odoo/addons/stock_picking_return_restricted_qty/wizard/__init__.py
odoo/addons/stock_picking_return_restricted_qty/wizard/stock_picking_return.py
odoo_addon_stock_picking_return_restricted_qty-18.0.1.0.0.4.dist-info/METADATA
odoo_addon_stock_picking_return_restricted_qty-18.0.1.0.0.4.dist-info/WHEEL
odoo_addon_stock_picking_return_restricted_qty-18.0.1.0.0.4.dist-info/top_level.txt
odoo_addon_stock_picking_return_restricted_qty-18.0.1.0.0.4.dist-info/RECORD
